setup.cfg
setup.py
bigcode/__init__.py
bigcode/apps.py
bigcode/compat.py
bigcode/settings.py
bigcode/utils.py
bigcode/widgets.py
bigcode.egg-info/PKG-INFO
bigcode.egg-info/SOURCES.txt
bigcode.egg-info/dependency_links.txt
bigcode.egg-info/requires.txt
bigcode.egg-info/top_level.txt
bigcode/templatetags/__init__.py
bigcode/templatetags/jazzmin.py