Metadata-Version: 2.1
Name: bigcode
Version: 1.0.10
Summary: BIGCODE is a place where you can easily and conveniently manage your website.
Home-page: https://github.com/ayhandev/bigcode_adminstration
Download-URL: https://github.com/ayhandev/bigcode_adminstration.git
Author: ayhan
Author-email: jumanyyazowayhan32@gmail.com
License: MIT
Classifier: License :: OSI Approved :: MIT License
Classifier: Operating System :: OS Independent
Classifier: Intended Audience :: Developers
Classifier: Programming Language :: Python :: 3
Classifier: Programming Language :: Python :: 3.10
Classifier: Programming Language :: Python :: Implementation :: CPython
